SysLib/SystemLib.cp310-win_amd64.pyd
SysLib/SystemLib.pyi
SysLib/__init__.py
SysLib/out/src/SysLib/SystemLib.pyi
SysTaskLib/MultiTaskAdvLib.cp310-win_amd64.pyd
SysTaskLib/MultiTaskAdvLib.pyi
SysTaskLib/MultiTaskLib.cp310-win_amd64.pyd
SysTaskLib/MultiTaskLib.pyi
SysTaskLib/ThreadLib.cp310-win_amd64.pyd
SysTaskLib/ThreadLib.pyi
SysTaskLib/__init__.py
SysTaskLib/out/src/SysTaskLib/MultiTaskAdvLib.pyi
SysTaskLib/out/src/SysTaskLib/MultiTaskLib.pyi
SysTaskLib/out/src/SysTaskLib/ThreadLib.pyi
systemlibapi-1.2601.702.dist-info/licenses/LICENSE
systemlibapi-1.2601.702.dist-info/METADATA
systemlibapi-1.2601.702.dist-info/WHEEL
systemlibapi-1.2601.702.dist-info/top_level.txt
systemlibapi-1.2601.702.dist-info/RECORD
