Metadata-Version: 2.4
Name: SystemLibAPI
Version: 1.2601.702
Summary: mySQLDBCtrlAPI Python package
Author-email: James Lin <tylin123@ms27.hinet.net>
License: Copyright (c) 2025 James Lin
Project-URL: Homepage, https://mis.gotech.biz
Requires-Python: >=3.10
License-File: LICENSE
Requires-Dist: psutil
Dynamic: license-file
